Gui.py
MANIFEST.in
README.rst
Templates.py
__init__.py
aboutDlg_ui.py
babel.ini
main_rc.py
mainform_ui.py
preferencesDlg_ui.py
qt_local.pro
setup.py
./Gui.py
./Templates.py
./__init__.py
./aboutDlg_ui.py
./main_rc.py
./mainform_ui.py
./preferencesDlg_ui.py
alfanousDesktop.egg-info/PKG-INFO
alfanousDesktop.egg-info/SOURCES.txt
alfanousDesktop.egg-info/dependency_links.txt
alfanousDesktop.egg-info/entry_points.txt
alfanousDesktop.egg-info/requires.txt
alfanousDesktop.egg-info/top_level.txt
locale/ar/LC_MESSAGES/alfanousDesktop.qm
locale/ar/LC_MESSAGES/alfanousDesktop.ts
locale/ar/LC_MESSAGES/alfanousJinjaT.mo
locale/ar/LC_MESSAGES/alfanousJinjaT.po
locale/es/LC_MESSAGES/alfanousDesktop.qm
locale/es/LC_MESSAGES/alfanousDesktop.ts
locale/es/LC_MESSAGES/alfanousJinjaT.mo
locale/es/LC_MESSAGES/alfanousJinjaT.po
locale/fr/LC_MESSAGES/alfanousDesktop.qm
locale/fr/LC_MESSAGES/alfanousDesktop.ts
locale/fr/LC_MESSAGES/alfanousJinjaT.mo
locale/fr/LC_MESSAGES/alfanousJinjaT.po
locale/id/LC_MESSAGES/alfanousDesktop.qm
locale/id/LC_MESSAGES/alfanousDesktop.ts
locale/id/LC_MESSAGES/alfanousJinjaT.mo
locale/id/LC_MESSAGES/alfanousJinjaT.po
locale/ms/LC_MESSAGES/alfanousDesktop.qm
locale/ms/LC_MESSAGES/alfanousDesktop.ts
locale/ms/LC_MESSAGES/alfanousJinjaT.mo
locale/ms/LC_MESSAGES/alfanousJinjaT.po
locale/sq/LC_MESSAGES/alfanousDesktop.qm
locale/sq/LC_MESSAGES/alfanousDesktop.ts
locale/sq/LC_MESSAGES/alfanousJinjaT.mo
locale/sq/LC_MESSAGES/alfanousJinjaT.po
templates/aya_results.html
templates/translation_results.html