Metadata-Version: 1.1
Name: alfanousDesktop
Version: 0.7.22
Summary: Desktop interface for alfanous Quranic search engine API
Home-page: http://www.alfanous.org/
Author: Assem Chelli
Author-email: assem.ch@gmail.com
License: AGPL
Keywords: quran search indexing engine alfanous
Platform: ALL
Classifier: Development Status :: 4 - Beta
Classifier: Intended Audience :: Religion
Classifier: License :: OSI Approved :: GNU General Public License (GPL)
Classifier: Natural Language :: Arabic
Classifier: Natural Language :: English
Classifier: Operating System :: OS Independent
Classifier: Programming Language :: Python :: 2.6
